components/password_guesser.v
module password_guesser (a, b, c, d, e);

    input a, b, c, d;
    output e;

    assign e = (!( ( (a && b) || (a && c))  || ( (c || (!c)) && ((!d) || (a)) ) ));

endmodule

components/password_setter.v
module password_setter (a, b, c, d, e);

    input a, b, c, d;
    output e;

    assign e = (!( ( (a && b) || (a && c))  || ( (c || (!c)) && ((!d) || (a)) ) ));

endmodule

tb_main.v
`include "components/password_setter.v"
`include "components/password_guesser.v"
module tb_main;


    reg a, b, c, d, v, w, x, y;
    wire e, z;
 

    password_setter setterInstance(a, b, c, d, e);
    password_guesser guesserInstance(v, w, x, y, z);
 
    initial begin
    $dumpfile("tb_main.vcd");
    $dumpvars(0, tb_main);
        a = 0; b = 0; c = 0; d = 0;
        #1
        a = 0; b = 0; c = 0; d = 1;
        #1
        a = 0; b = 0; c = 1; d = 0;
        #1
        a = 0; b = 0; c = 1; d = 1;
        #1
        a = 0; b = 1; c = 0; d = 0;
        #1
        a = 0; b = 1; c = 0; d = 1;
        #1
        a = 0; b = 1; c = 1; d = 0;
        #1
        a = 0; b = 1; c = 1; d = 1;
        #1
        a = 1; b = 0; c = 0; d = 0;
        #1
        a = 1; b = 0; c = 0; d = 1;
        #1
        a = 1; b = 0; c = 1; d = 0;
        #1
        a = 1; b = 0; c = 1; d = 1;
        #1
        a = 1; b = 1; c = 0; d = 0;
        #1
        a = 1; b = 1; c = 0; d = 1;
        #1
        a = 1; b = 1; c = 1; d = 0;
        #1
        a = 1; b = 1; c = 1; d = 1;
        #1;
    end

    initial begin
    $dumpfile("tb_main.vcd");
    $dumpvars(0, tb_main);
        v = 0; w = 0; x = 0; y = 0;
        #1
        v = 0; w = 0; x = 0; y = 1;
        #1
        v = 0; w = 0; x = 1; y = 0;
        #1
        v = 0; w = 0; x = 1; y = 1;
        #1
        v = 0; w = 1; x = 0; y = 0;
        #1
        v = 0; w = 1; x = 0; y = 1;
        #1
        v = 0; w = 1; x = 1; y = 0;
        #1
        v = 0; w = 1; x = 1; y = 1;
        #1
        v = 1; w = 0; x = 0; y = 0;
        #1
        v = 1; w = 0; x = 0; y = 1;
        #1
        v = 1; w = 0; x = 1; y = 0;
        #1
        v = 1; w = 0; x = 1; y = 1;
        #1
        v = 1; w = 1; x = 0; y = 0;
        #1
        v = 1; w = 1; x = 0; y = 1;
        #1
        v = 1; w = 1; x = 1; y = 0;
        #1
        v = 1; w = 1; x = 1; y = 1;
        #1;
    end
 
endmodule

tb_main.vcd
$date
	Tue Dec 20 10:43:30 2022
$end
$version
	Icarus Verilog
$end
$timescale
	1s
$end
$scope module tb_main $end
$var wire 1 ! e $end
$var wire 1 " z $end
$var reg 1 # a $end
$var reg 1 $ b $end
$var reg 1 % c $end
$var reg 1 & d $end
$var reg 1 ' v $end
$var reg 1 ( w $end
$var reg 1 ) x $end
$var reg 1 * y $end
$scope module setterInstance $end
$var wire 1 + a $end
$var wire 1 , b $end
$var wire 1 - c $end
$var wire 1 . d $end
$var wire 1 ! e $end
$upscope $end
$scope module guesserInstance $end
$var wire 1 / a $end
$var wire 1 0 b $end
$var wire 1 1 c $end
$var wire 1 2 d $end
$var wire 1 " e $end
$upscope $end
$upscope $end
$scope module tb_main $end
$scope module setterInstance $end
$upscope $end
$scope module guesserInstance $end
$upscope $end
$upscope $end
$enddefinitions $end
#0
$dumpvars
02
01
00
0/
0.
0-
0,
0+
0*
0)
0(
0'
0&
0%
0$
0#
0"
0!
$end
#1
1"
1!
1*
12
1&
1.
#2
0"
0!
0*
02
1)
11
0&
0.
1%
1-
#3
1"
1!
1*
12
1&
1.
#4
0"
0!
0*
02
0)
01
1(
10
0&
0.
0%
0-
1$
1,
#5
1"
1!
1*
12
1&
1.
#6
0"
0!
0*
02
1)
11
0&
0.
1%
1-
#7
1"
1!
1*
12
1&
1.
#8
0"
0!
0*
02
0)
01
0(
00
1'
1/
0&
0.
0%
0-
0$
0,
1#
1+
#9
1*
12
1&
1.
#10
0*
02
1)
11
0&
0.
1%
1-
#11
1*
12
1&
1.
#12
0*
02
0)
01
1(
10
0&
0.
0%
0-
1$
1,
#13
1*
12
1&
1.
#14
0*
02
1)
11
0&
0.
1%
1-
#15
1*
12
1&
1.
